pyrepeat/VERSION
pyrepeat/__init__.py
pyrepeat/repeat.py
pyrepeat-2.0.dist-info/DESCRIPTION.rst
pyrepeat-2.0.dist-info/METADATA
pyrepeat-2.0.dist-info/RECORD
pyrepeat-2.0.dist-info/WHEEL
pyrepeat-2.0.dist-info/entry_points.txt
pyrepeat-2.0.dist-info/metadata.json
pyrepeat-2.0.dist-info/top_level.txt
