Metadata-Version: 2.0
Name: pyrepeat
Version: 2.0
Summary: Repeat command
Home-page: https://github.com/itsapinhulk/pyrepeat
Author: UNKNOWN
Author-email: UNKNOWN
License: MIT
Keywords: console utility repeat
Platform: UNKNOWN
Classifier: Development Status :: 5 - Production/Stable
Classifier: Environment :: Console
Classifier: Intended Audience :: Developers
Classifier: License :: OSI Approved :: MIT License
Classifier: Programming Language :: Python :: 2
Classifier: Programming Language :: Python :: 3
Classifier: Operating System :: POSIX :: Linux
Classifier: Topic :: System :: Shells
Classifier: Topic :: Utilities
